overtalk.py
overtalk-0.0.2.dist-info/LICENSE.txt
overtalk-0.0.2.dist-info/METADATA
overtalk-0.0.2.dist-info/WHEEL
overtalk-0.0.2.dist-info/top_level.txt
overtalk-0.0.2.dist-info/RECORD
