Metadata-Version: 2.1
Name: overtalk
Version: 0.0.2
Summary: Computes duration of overtalk in a stereo WAV file.
Home-page: https://github.com/sszokoly/overtalk
Author: Szabolcs Szokoly
Author-email: szokoly@protonmail.com
Maintainer: Szabolcs Szokoly
Maintainer-email: sszokoly@protonmail.com
License: MIT
Keywords: VoIP telephony audio analysis overtalk
Platform: UNKNOWN
Classifier: Environment :: Console
Classifier: Development Status :: 4 - Beta
Classifier: Intended Audience :: Developers
Classifier: Topic :: Multimedia :: Sound/Audio :: Analysis
Classifier: Programming Language :: Python :: 3
Classifier: Operating System :: OS Independent
Classifier: License :: OSI Approved :: MIT License
Requires-Python: >=3.6
Requires-Dist: auditok
